Metadata-Version: 1.2
Name: mkwvconf
Version: 0.1.1
Summary: Automatically generate a wvdial configuration for mobile broadband devices using mobile-broadband-provider-info
Home-page: https://github.com/ascoderu/mkwvconf
Author: Clemens Wolff
Author-email: clemens.wolff+pypi@gmail.com
License: Apache Software License
Download-URL: https://pypi.python.org/pypi/mkwvconf
Platform: UNKNOWN
Classifier: Development Status :: 5 - Production/Stable
Classifier: License :: OSI Approved :: Apache Software License
Classifier: Programming Language :: Python :: 2.7
Classifier: Programming Language :: Python :: 3.4
Classifier: Programming Language :: Python :: 3.5
Classifier: Programming Language :: Python :: 3.6
Classifier: Topic :: Utilities
Requires-Python: >=2.7.*,!=3.0.*,!=3.1.*,!=3.2.*,!=3.3.*
